.gitignore
LICENSE
README.md
config.ini.example
requirements.txt
setup.cfg
setup.py
.github/workflows/python-app.yml
crypto_reflex/__init__.py
crypto_reflex/backtest_exchange.py
crypto_reflex/backtester.py
crypto_reflex/ccxt_exchange.py
crypto_reflex/crypto_reflex_lib.py
crypto_reflex/dummy_exchange.py
crypto_reflex/executor.py
crypto_reflex/main.py
crypto_reflex/order.py
crypto_reflex/portfolio.py
crypto_reflex/simple_balancer.py
crypto_reflex/tests.py
crypto_reflex.egg-info/PKG-INFO
crypto_reflex.egg-info/SOURCES.txt
crypto_reflex.egg-info/dependency_links.txt
crypto_reflex.egg-info/entry_points.txt
crypto_reflex.egg-info/requires.txt
crypto_reflex.egg-info/top_level.txt
data/BNB-BTC.json
data/BNB-ETH.json
data/BNB-USDT.json
data/BTC-USD.json
data/BTC-USDT.json
data/ETH-BTC.json
data/ETH-USD.json
data/ETH-USDT.json
data/XRP-BNB.json
data/XRP-BTC.json
data/XRP-ETH.json
data/XRP-USD.json
data/XRP-USDT.json