Metadata-Version: 2.1
Name: crypto-reflex
Version: 1.0.1
Summary: A tool to automatically balance cryptocurrency portfolios
Home-page: https://github.com/draczer01/Crypto_Reflex
Author: Draczer01
Author-email: draczer01@gmail.com
License: MIT
Keywords: cryptocurrency,portfolio,xrp,ethereum,bitcoin,btc,eth,balancer,rebalancer
Classifier: Development Status :: 5 - Production/Stable
Classifier: Intended Audience :: End Users/Desktop
Classifier: Intended Audience :: Financial and Insurance Industry
Classifier: Topic :: Office/Business :: Financial :: Investment
Classifier: License :: OSI Approved :: MIT License
Classifier: Programming Language :: Python :: 3
Classifier: Programming Language :: Python :: 3.9
License-File: LICENSE
